dispatcher_plugin_nb2workflow/__init__.py
dispatcher_plugin_nb2workflow/dataserver_dispatcher.py
dispatcher_plugin_nb2workflow/exposer.py
dispatcher_plugin_nb2workflow/products.py
dispatcher_plugin_nb2workflow/queries.py
dispatcher_plugin_nb2workflow-0.0.1.dist-info/METADATA
dispatcher_plugin_nb2workflow-0.0.1.dist-info/WHEEL
dispatcher_plugin_nb2workflow-0.0.1.dist-info/top_level.txt
dispatcher_plugin_nb2workflow-0.0.1.dist-info/RECORD
