Metadata-Version: 2.1
Name: dispatcher-plugin-nb2workflow
Version: 0.0.1
Requires-Dist: cdci-data-analysis
Provides-Extra: test
Requires-Dist: pytest ; extra == 'test'
Requires-Dist: psutil ; extra == 'test'
